order/__init__.py
order/admin.py
order/apps.py
order/models.py
order/tests.py
order/urls.py
order/views.py
order/migrations/__init__.py
django_paytring-1.0.0.dist-info/LICENSE
django_paytring-1.0.0.dist-info/METADATA
django_paytring-1.0.0.dist-info/WHEEL
django_paytring-1.0.0.dist-info/top_level.txt
django_paytring-1.0.0.dist-info/RECORD
