Metadata-Version: 2.1
Name: django-paytring
Version: 1.0.0
Summary: A Django app helps to create/fetch an order, subscription-plan, subscription on Paytring.
Home-page: https://paytring.com/
Author: Paytring
Author-email: developer@paytring.com
Maintainer-email: developer@paytring.com
License: MIT
Classifier: Environment :: Web Environment
Classifier: Framework :: Django
Classifier: Intended Audience :: Developers
Classifier: License :: OSI Approved :: MIT License
Classifier: Operating System :: OS Independent
Classifier: Programming Language :: Python
Classifier: Programming Language :: Python :: 3
Classifier: Programming Language :: Python :: 3 :: Only
Classifier: Programming Language :: Python :: 3.10
Classifier: Programming Language :: Python :: 3.11
Classifier: Programming Language :: Python :: 3.12
Classifier: Topic :: Software Development :: Libraries :: Python Modules
License-File: LICENSE
Requires-Dist: paytring (==1.0.7)
Requires-Dist: djangorestframework (>=3.12.0)
